{
  "schema_version" : "v1",
  "generated_at" : "2026-03-24T14:57:20.654186400+09:00",
  "model_id" : "public_water_support:AK2310900",
  "route_type" : "public_water_support",
  "route_key" : "AK2310900",
  "template_kind" : "public_water_support_page",
  "render_path" : "/public-water-system/AK2310900",
  "generation_mode" : "static_file_seed",
  "indexable" : true,
  "last_verified_date" : "2026-03-20",
  "source_count" : 4,
  "payload" : {
    "system" : {
      "pwsid" : "AK2310900",
      "pwsName" : "College Utilities Corporation",
      "stateCode" : "AK",
      "systemType" : "community",
      "populationServed" : "27000",
      "sourceWaterType" : "purchased_groundwater",
      "utilityWebsiteUrl" : "https://www.myutility.us/akwater",
      "ccrUrl" : "https://www.myutility.us/docs/default-source/akwater/water-quality-reports/college-utilities/2025/cuc-ccr-2025.pdf",
      "pfasNoticeUrl" : "https://www.myutility.us/docs/default-source/akwater/water-quality-reports/college-utilities/2025/cuc-ccr-2025.pdf",
      "serviceAreaNotes" : "Fairbanks-area community system with purchased groundwater supply and 2024 PFAS values reported in the 2025 utility water quality report",
      "lastVerifiedDate" : "2026-03-20",
      "sourceIds" : [ "alaska-water-home", "alaska-water-quality-reports", "alaska-dww-college-utilities-monitoring-summary", "college-utilities-2025-water-quality-report" ]
    }
  }
}