{
  "schema_version" : "v1",
  "generated_at" : "2026-03-24T14:57:20.645177800+09:00",
  "model_id" : "filter_product:zerowater-30-cup-dispenser-bundle",
  "route_type" : "filter_product",
  "route_key" : "zerowater-30-cup-dispenser-bundle",
  "template_kind" : "filter_product_page",
  "render_path" : "/filters/zerowater-30-cup-dispenser-bundle",
  "generation_mode" : "static_file_seed",
  "indexable" : true,
  "last_verified_date" : "2026-03-20",
  "source_count" : 3,
  "payload" : {
    "filter_product" : {
      "routeType" : "filter_product",
      "routeKey" : "zerowater-30-cup-dispenser-bundle",
      "title" : "ZeroWater 30 Cup Ready-Pour Dispenser + 2 Filters PFAS record",
      "lede" : "Certification scope, upkeep, and seller path for ZeroWater 30 Cup Ready-Pour Dispenser + 2 Filters are kept on one page so the buying decision stays inspectable.",
      "eyebrow" : "Product record",
      "canonicalPath" : "/filters/zerowater-30-cup-dispenser-bundle",
      "lastVerifiedDate" : "2026-03-20",
      "sourceCount" : 3,
      "merchantLabel" : "ZeroWater",
      "brandPath" : "/filters/brands/zerowater",
      "installationPath" : "/filters/installations/dispenser",
      "filterTypePath" : "/filters/types/ion-exchange",
      "merchantPath" : "/filters/merchants/zerowater",
      "highlights" : [ "IAPMO 042|053 / PFAS coverage PFOA, PFOS", "Upfront $71.98 / Annualized Maintenance not normalized", "Best for Best for low-commitment households that prioritize a narrow intervention and simple setup. / Not for Not for households that want high-capacity flow with minimal refill friction." ],
      "keywords" : [ "zerowater-30-cup-dispenser-bundle", "ZeroWater", "30 Cup Ready-Pour Dispenser + 2 Filters", "ZeroWater 30 Cup Ready-Pour Dispenser + 2 Filters", "Ion Exchange", "Dispenser", "ZeroWater", "PFAS filter", "certified PFAS filter" ],
      "product" : {
        "productId" : "zerowater-30-cup-dispenser-bundle",
        "brand" : "ZeroWater",
        "model" : "30 Cup Ready-Pour Dispenser + 2 Filters",
        "filterType" : "ion_exchange",
        "installationType" : "dispenser",
        "certBody" : "IAPMO",
        "standardCode" : "042|053",
        "listingRecordId" : "zerowater-30-cup-dispenser-bundle",
        "claimNames" : [ "PFOA Reduction", "PFOS Reduction" ],
        "coveredPfas" : [ "PFOA", "PFOS" ],
        "listingUrl" : "https://www.zerowater.com/products/subscription-bundle-offer-30-cup-water-filter-ready-pour-dispenser-2pk-filters",
        "replacementCadenceMonths" : null,
        "replacementCapacityGallons" : null,
        "upfrontCostUsd" : 71.98,
        "replacementCostUsd" : null,
        "membraneCostUsd" : null,
        "serviceCostUsd" : null,
        "recurringCostComponents" : [ ],
        "priceObservedAt" : "2026-03-20",
        "costConfidence" : "medium",
        "sourceIds" : [ "zerowater-30-cup-dispenser-bundle-product", "zerowater-performance-certification", "zerowater-certified-devices-performance-pdf" ]
      },
      "relatedProducts" : [ {
        "productId" : "zerowater-23-cup-dispenser",
        "brand" : "ZeroWater",
        "model" : "23 Cup 5-Stage Water Filter Dispenser",
        "filterType" : "ion_exchange",
        "installationType" : "dispenser",
        "certBody" : "IAPMO",
        "standardCode" : "042|053",
        "listingRecordId" : "zerowater-23-cup-dispenser",
        "claimNames" : [ "PFOA Reduction", "PFOS Reduction" ],
        "coveredPfas" : [ "PFOA", "PFOS" ],
        "listingUrl" : "https://www.zerowater.com/products/zerowater-23-cup-dispenser",
        "replacementCadenceMonths" : null,
        "replacementCapacityGallons" : null,
        "upfrontCostUsd" : 39.99,
        "replacementCostUsd" : null,
        "membraneCostUsd" : null,
        "serviceCostUsd" : null,
        "recurringCostComponents" : [ ],
        "priceObservedAt" : "2026-03-20",
        "costConfidence" : "medium",
        "sourceIds" : [ "zerowater-23-cup-dispenser-product", "zerowater-performance-certification", "zerowater-certified-devices-performance-pdf" ]
      }, {
        "productId" : "zerowater-10-cup-pitcher",
        "brand" : "ZeroWater",
        "model" : "10 Cup Pitcher",
        "filterType" : "ion_exchange",
        "installationType" : "pitcher",
        "certBody" : "IAPMO",
        "standardCode" : "042|053",
        "listingRecordId" : "zerowater-10-cup-pitcher",
        "claimNames" : [ "PFOA Reduction", "PFOS Reduction" ],
        "coveredPfas" : [ "PFOA", "PFOS" ],
        "listingUrl" : "https://www.zerowater.com/products/10-cup-water-filter-pitcher",
        "replacementCadenceMonths" : null,
        "replacementCapacityGallons" : null,
        "upfrontCostUsd" : 37.99,
        "replacementCostUsd" : null,
        "membraneCostUsd" : null,
        "serviceCostUsd" : null,
        "recurringCostComponents" : [ ],
        "priceObservedAt" : "2026-03-20",
        "costConfidence" : "medium",
        "sourceIds" : [ "zerowater-10-cup-pitcher-product", "zerowater-performance-certification", "zerowater-certified-devices-performance-pdf" ]
      }, {
        "productId" : "zerowater-5-gallon-cooler",
        "brand" : "ZeroWater",
        "model" : "5-Gallon Water Cooler Dispenser",
        "filterType" : "ion_exchange",
        "installationType" : "cooler_dispenser",
        "certBody" : "IAPMO",
        "standardCode" : "042|053",
        "listingRecordId" : "zerowater-5-gallon-cooler",
        "claimNames" : [ "PFOA Reduction", "PFOS Reduction" ],
        "coveredPfas" : [ "PFOA", "PFOS" ],
        "listingUrl" : "https://www.zerowater.com/products/filtered-water-cooler",
        "replacementCadenceMonths" : null,
        "replacementCapacityGallons" : null,
        "upfrontCostUsd" : 69.99,
        "replacementCostUsd" : null,
        "membraneCostUsd" : null,
        "serviceCostUsd" : null,
        "recurringCostComponents" : [ ],
        "priceObservedAt" : "2026-03-20",
        "costConfidence" : "medium",
        "sourceIds" : [ "zerowater-5-gallon-cooler-product", "zerowater-performance-certification", "zerowater-certified-devices-performance-pdf" ]
      }, {
        "productId" : "zerowater-7-cup-pitcher",
        "brand" : "ZeroWater",
        "model" : "7 Cup Ready-Pour Pitcher",
        "filterType" : "ion_exchange",
        "installationType" : "pitcher",
        "certBody" : "IAPMO",
        "standardCode" : "042|053",
        "listingRecordId" : "zerowater-7-cup-pitcher",
        "claimNames" : [ "PFOA Reduction", "PFOS Reduction" ],
        "coveredPfas" : [ "PFOA", "PFOS" ],
        "listingUrl" : "https://www.zerowater.com/products/7-cup-water-filter-pitcher",
        "replacementCadenceMonths" : null,
        "replacementCapacityGallons" : null,
        "upfrontCostUsd" : 24.99,
        "replacementCostUsd" : null,
        "membraneCostUsd" : null,
        "serviceCostUsd" : null,
        "recurringCostComponents" : [ ],
        "priceObservedAt" : "2026-03-20",
        "costConfidence" : "medium",
        "sourceIds" : [ "zerowater-7-cup-pitcher-product", "zerowater-performance-certification", "zerowater-certified-devices-performance-pdf" ]
      } ]
    }
  }
}